anglerfish/__init__.py
anglerfish/__main__.py
anglerfish/anglerfish.py
anglerfish/cli.py
anglerfish/config/__init__.py
anglerfish/config/adaptors.yaml
anglerfish/demux/__init__.py
anglerfish/demux/adaptor.py
anglerfish/demux/demux.py
anglerfish/demux/report.py
anglerfish/demux/samplesheet.py
anglerfish/explore/__init__.py
anglerfish/explore/entropy.py
anglerfish/explore/explore.py
bio_anglerfish-0.7.0.dist-info/LICENSE
bio_anglerfish-0.7.0.dist-info/METADATA
bio_anglerfish-0.7.0.dist-info/WHEEL
bio_anglerfish-0.7.0.dist-info/entry_points.txt
bio_anglerfish-0.7.0.dist-info/top_level.txt
bio_anglerfish-0.7.0.dist-info/RECORD
