Metadata-Version: 2.1
Name: bio-anglerfish
Version: 0.7.0
Summary: Anglerfish, a tool to demultiplex Illumina libraries from ONT data
Home-page: https://github.com/NationalGenomicsInfrastructure/anglerfish
Author: Remi-Andre Olsen
Author-email: remi-andre.olsen@scilifelab.se
License: MIT
Classifier: Development Status :: 5 - Production/Stable
Classifier: Environment :: Console
Classifier: Intended Audience :: Developers
Classifier: Intended Audience :: Healthcare Industry
Classifier: Intended Audience :: Science/Research
Classifier: License :: OSI Approved :: MIT License
Classifier: Operating System :: POSIX :: Linux
Classifier: Programming Language :: Python
Classifier: Topic :: Scientific/Engineering
Classifier: Topic :: Scientific/Engineering :: Medical Science Apps.
Classifier: Topic :: Scientific/Engineering :: Bio-Informatics
Requires-Python: >=3.12
License-File: LICENSE
Requires-Dist: bio
Requires-Dist: biopython==1.83
Requires-Dist: numpy==1.26.3
Requires-Dist: pandas==2.1.4
Requires-Dist: pytest==8.2.1
Requires-Dist: python-levenshtein==0.23.0
Requires-Dist: pyyaml==6.0.1
Requires-Dist: setuptools
Requires-Dist: typer==0.9.0
Requires-Dist: typing-extensions
Provides-Extra: dev
Requires-Dist: ruff; extra == "dev"
Requires-Dist: mypy; extra == "dev"
Requires-Dist: editorconfig-checker; extra == "dev"
